yakyak/__init__.py
yakyak/__main__.py
yakyak/yakyak.py
yakyak-1.6.3.dist-info/LICENSE.md
yakyak-1.6.3.dist-info/METADATA
yakyak-1.6.3.dist-info/WHEEL
yakyak-1.6.3.dist-info/entry_points.txt
yakyak-1.6.3.dist-info/top_level.txt
yakyak-1.6.3.dist-info/RECORD
